ChangeLog.txt
MANIFEST.in
README.md
TODO.txt
active_directory.py
setup.py
active_directory.egg-info/PKG-INFO
active_directory.egg-info/SOURCES.txt
active_directory.egg-info/dependency_links.txt
active_directory.egg-info/requires.txt
active_directory.egg-info/top_level.txt