Metadata-Version: 1.0
Name: active-directory
Version: 0.67.1
Summary: Active Directory
Home-page: http://timgolden.me.uk/python/active_directory.html
Author: Tim Golden
Author-email: mail@timgolden.me.uk
License: http://www.opensource.org/licenses/mit-license.php
Platform: UNKNOWN
